halo5/__init__.py
halo5/base.py
halo5/client.py
halo5/entity.py
halo5/metadata.py
halo5/profile.py
halo5/stats.py
halo5/ugc.py
halo5/tests/__init__.py
halo5/tests/test_all.py
halo5.py-0.3.0.dist-info/DESCRIPTION.rst
halo5.py-0.3.0.dist-info/METADATA
halo5.py-0.3.0.dist-info/RECORD
halo5.py-0.3.0.dist-info/WHEEL
halo5.py-0.3.0.dist-info/metadata.json
halo5.py-0.3.0.dist-info/top_level.txt
